mseep_ocode-0.1.0.dist-info/licenses/LICENSE
ocode_python/__init__.py
ocode_python/core/__init__.py
ocode_python/core/api_client.py
ocode_python/core/checkpoint.py
ocode_python/core/cli.py
ocode_python/core/context_manager.py
ocode_python/core/engine.py
ocode_python/core/error_recovery.py
ocode_python/core/orchestrator.py
ocode_python/core/semantic_context.py
ocode_python/core/session.py
ocode_python/core/stream_processor.py
ocode_python/languages/__init__.py
ocode_python/languages/base.py
ocode_python/languages/markdown.py
ocode_python/languages/python.py
ocode_python/languages/terraform.py
ocode_python/languages/typescript.py
ocode_python/languages/yaml.py
ocode_python/mcp/__init__.py
ocode_python/mcp/manager.py
ocode_python/mcp/protocol.py
ocode_python/mcp/server.py
ocode_python/tools/__init__.py
ocode_python/tools/agent_tool.py
ocode_python/tools/architect_tool.py
ocode_python/tools/base.py
ocode_python/tools/bash_tool.py
ocode_python/tools/curl_tool.py
ocode_python/tools/data_tools.py
ocode_python/tools/diff_tool.py
ocode_python/tools/env_tool.py
ocode_python/tools/file_edit_tool.py
ocode_python/tools/file_ops_tool.py
ocode_python/tools/file_tools.py
ocode_python/tools/find_tool.py
ocode_python/tools/git_advanced_tools.py
ocode_python/tools/git_tools.py
ocode_python/tools/glob_tool.py
ocode_python/tools/grep_tool.py
ocode_python/tools/head_tail_tool.py
ocode_python/tools/ls_tool.py
ocode_python/tools/mcp_tool.py
ocode_python/tools/memory_tools.py
ocode_python/tools/notebook_tools.py
ocode_python/tools/ping_tool.py
ocode_python/tools/process_tool.py
ocode_python/tools/search_tool.py
ocode_python/tools/session_tool.py
ocode_python/tools/shell_tools.py
ocode_python/tools/shell_tools_enhanced.py
ocode_python/tools/shell_tools_migration.py
ocode_python/tools/sticker_tool.py
ocode_python/tools/test_tools.py
ocode_python/tools/text_tools.py
ocode_python/tools/think_tool.py
ocode_python/tools/wc_tool.py
ocode_python/tools/which_tool.py
ocode_python/ui/__init__.py
ocode_python/ui/components.py
mseep_ocode-0.1.0.dist-info/METADATA
mseep_ocode-0.1.0.dist-info/WHEEL
mseep_ocode-0.1.0.dist-info/top_level.txt
mseep_ocode-0.1.0.dist-info/RECORD
