Metadata-Version: 2.4
Name: mseep-ocode
Version: 0.1.0
Summary: Terminal-native AI coding assistant powered by Ollama models
Home-page: https://github.com/mseep
Author: mseep
Author-email: support@skydeck.ai
Maintainer: mseep
Maintainer-email: support@skydeck.ai
Keywords: mseep
Classifier: Programming Language :: Python :: 3
Classifier: License :: OSI Approved :: MIT License
Classifier: Operating System :: OS Independent
Requires-Python: >=3.6
License-File: LICENSE
Requires-Dist: aiohttp>=3.9
Requires-Dist: click>=8.1
Requires-Dist: rich>=13
Requires-Dist: gitpython>=3.1
Requires-Dist: tree-sitter>=0.20
Requires-Dist: pydantic>=2
Requires-Dist: pyyaml>=6
Requires-Dist: prompt-toolkit>=3
Requires-Dist: aiofiles>=23
Requires-Dist: watchdog>=3
Requires-Dist: pexpect>=4.9.0
Requires-Dist: psutil>=5.9.0
Requires-Dist: jsonpath-ng>=1.5.3
Requires-Dist: python-dotenv>=1.0.0
Requires-Dist: requests>=2.31.0
Dynamic: author
Dynamic: author-email
Dynamic: classifier
Dynamic: description
Dynamic: description-content-type
Dynamic: home-page
Dynamic: keywords
Dynamic: license-file
Dynamic: maintainer
Dynamic: maintainer-email
Dynamic: requires-dist
Dynamic: requires-python
Dynamic: summary
